ethon/__init__.py
ethon/mystarts.py
ethon/pyfunc.py
ethon/pyutils.py
ethon/teleutils.py
ethon-69.2.dist-info/LICENSE.txt
ethon-69.2.dist-info/METADATA
ethon-69.2.dist-info/WHEEL
ethon-69.2.dist-info/top_level.txt
ethon-69.2.dist-info/RECORD
